matematikk/__init__.py
matematikk/_exports/def_alle_svar_eksamen_mas.py
matematikk/_exports/def_alle_svar_okonomi_mas.py
matematikk/_exports/def_deriver_mas.py
matematikk/_exports/def_ekstremalpunkt_max_mas.py
matematikk/_exports/def_ekstremalpunkt_max_matematikk_mas.py
matematikk/_exports/def_enhet_fra_overskudd_max_mas.py
matematikk/_exports/def_enhet_fra_overskudd_max_med_kostnad_mas.py
matematikk/_exports/def_enhet_og_pris_fra_inntekt_max_mas.py
matematikk/_exports/def_farge_txt_mas.py
matematikk/_exports/def_normalfordeling_standard_mas.py
matematikk/_exports/def_okonomi_mas.py
matematikk/_exports/def_oppg_strek_mas.py
matematikk/_exports/def_reggis_mas.py
matematikk/_exports/def_reggis_matematikk_mas.py
matematikk/_exports/def_sjekk_datatype_mas.py
matematikk/_exports/def_spinner_mas.py
matematikk/_exports/def_superlos_mas.py
matematikk/_exports/def_superlos_matematikk_mas.py
matematikk/_exports/def_tabell_mas.py
matematikk/_exports/def_vekstfaktor.py
matematikk/_exports/def_vekstfaktor_cas.py
matematikk/_exports/def_vekstfaktor_cas_sympy.py
matematikk/python/eksamen/1t/2022-h/del-1/03/oppg-3-a-rasjonal-funksjon-bug.py
matematikk/python/eksamen/1t/2022-h/del-1/03/oppg-3-b-1-rasjonal-funksjon-if-else.py
matematikk/python/eksamen/1t/2022-h/del-1/03/oppg-3-b-2-rasjonal-funksjon-if.py
matematikk/python/eksamen/1t/2022-v/del-1/04/oppg-4-kvadrattall.py
matematikk/python/eksamen/s1/2023-h/del-1/05/oppg-5-grensekostnad.py
matematikk/python/eksamen/s1/2023-h/del-2/01/01-oppg-1-a-1-sofa-mas.py
matematikk/python/eksamen/s1/2023-h/del-2/01/01-oppg-1-a-2-sofa-def-reggis-str-mas.py
matematikk/python/eksamen/s1/2023-h/del-2/01/01-oppg-1-a-3-sofa-def-reggis-cas-mas.py
matematikk/python/eksamen/s1/2023-h/del-2/01/01-oppg-1-a-4-sofa-matematikk-mas.py
matematikk/python/eksamen/s1/2023-h/del-2/01/01-oppg-1-a-5-sofa-matematikk-speedrun-mas.py
matematikk/python/eksamen/s1/2023-h/del-2/01/01-oppg-1-b-1-sofa-mas.py
matematikk-0.0.227.dist-info/LICENCE
matematikk-0.0.227.dist-info/METADATA
matematikk-0.0.227.dist-info/WHEEL
matematikk-0.0.227.dist-info/top_level.txt
matematikk-0.0.227.dist-info/RECORD
