Metadata-Version: 2.1
Name: matematikk
Version: 0.0.227
Summary: Matematikk-bibliotek
Author-email: matematikk <kontakt@matematikk.as>
Project-URL: Homepage, https://matematikk.as
Project-URL: Issues, https://matematikk.as
Classifier: Programming Language :: Python :: 3
Classifier: License :: OSI Approved :: MIT License
Classifier: Operating System :: OS Independent
Requires-Python: >=3.8
License-File: LICENCE
